dbrouter/__init__.py
dbrouter/_parse_database_url.py
dbrouter/by_app.py
dbrouter/restrict_migrations.py
dbrouter/version.py
django_dbrouter-0.1.4.post2.dist-info/METADATA
django_dbrouter-0.1.4.post2.dist-info/WHEEL
django_dbrouter-0.1.4.post2.dist-info/top_level.txt
django_dbrouter-0.1.4.post2.dist-info/RECORD
